rnzb-0.6.0.dist-info/RECORD
rnzb-0.6.0.dist-info/WHEEL
rnzb-0.6.0.dist-info/METADATA
rnzb-0.6.0.dist-info/licenses/LICENSE-APACHE
rnzb-0.6.0.dist-info/licenses/LICENSE-MIT
rnzb/__init__.pyi
rnzb/rnzb.pypy311-pp73-darwin.so
rnzb/__init__.py
rnzb/py.typed
