Metadata-Version: 2.4
Name: rnzb
Version: 0.6.0
Classifier: Intended Audience :: Developers
Classifier: Operating System :: OS Independent
Classifier: Programming Language :: Rust
Classifier: Programming Language :: Python :: 3.9
Classifier: Programming Language :: Python :: 3.10
Classifier: Programming Language :: Python :: 3.11
Classifier: Programming Language :: Python :: 3.12
Classifier: Programming Language :: Python :: 3.13
Classifier: Programming Language :: Python :: 3.14
Classifier: Programming Language :: Python :: Implementation :: CPython
Classifier: Programming Language :: Python :: Implementation :: PyPy
Classifier: Typing :: Typed
License-File: LICENSE-APACHE
License-File: LICENSE-MIT
Summary: Python bindings to the nzb-rs library - a spec compliant parser for NZB files, written in Rust.
Keywords: nzb,usenet,parser
Author-email: Ravencentric <me@ravencentric.cc>
License-Expression: MIT OR Apache-2.0
Requires-Python: >=3.9
Project-URL: Repository, https://github.com/Ravencentric/rnzb
